pytimetk/__init__.py
pytimetk/_polars_compat.py
pytimetk/core/__init__.py
pytimetk/core/acf_diagnostics.py
pytimetk/core/anomalize.py
pytimetk/core/apply_by_time.py
pytimetk/core/correlationfunnel.py
pytimetk/core/filter_by_time.py
pytimetk/core/frequency.py
pytimetk/core/future.py
pytimetk/core/make_future_timeseries.py
pytimetk/core/make_timeseries_sequence.py
pytimetk/core/pad.py
pytimetk/core/seasonal_diagnostics.py
pytimetk/core/stl_diagnostics.py
pytimetk/core/summarize_by_time.py
pytimetk/core/ts_features.py
pytimetk/core/ts_summary.py
pytimetk/crossvalidation/__init__.py
pytimetk/crossvalidation/time_series_cv.py
pytimetk/datasets/__init__.py
pytimetk/datasets/bike_sales_sample.csv
pytimetk/datasets/bike_sharing_daily.csv
pytimetk/datasets/expedia.csv
pytimetk/datasets/get_datasets.py
pytimetk/datasets/m4_daily.csv
pytimetk/datasets/m4_hourly.csv
pytimetk/datasets/m4_monthly.csv
pytimetk/datasets/m4_quarterly.csv
pytimetk/datasets/m4_weekly.csv
pytimetk/datasets/m4_yearly.csv
pytimetk/datasets/stocks_daily.csv
pytimetk/datasets/taylor_30_min.csv
pytimetk/datasets/walmart_sales_weekly.csv
pytimetk/datasets/wikipedia_traffic_daily.csv
pytimetk/feature_engineering/__init__.py
pytimetk/feature_engineering/_shift_utils.py
pytimetk/feature_engineering/diffs.py
pytimetk/feature_engineering/ewm.py
pytimetk/feature_engineering/expanding.py
pytimetk/feature_engineering/expanding_apply.py
pytimetk/feature_engineering/fourier.py
pytimetk/feature_engineering/hilbert.py
pytimetk/feature_engineering/holiday_signature.py
pytimetk/feature_engineering/lags.py
pytimetk/feature_engineering/leads.py
pytimetk/feature_engineering/pct_change.py
pytimetk/feature_engineering/rolling.py
pytimetk/feature_engineering/rolling_apply.py
pytimetk/feature_engineering/spline.py
pytimetk/feature_engineering/timeseries_signature.py
pytimetk/feature_engineering/wavelet.py
pytimetk/feature_store/__init__.py
pytimetk/feature_store/mlflow_integration.py
pytimetk/feature_store/store.py
pytimetk-2.4.0.dist-info/LICENSE
pytimetk-2.4.0.dist-info/METADATA
pytimetk-2.4.0.dist-info/WHEEL
pytimetk-2.4.0.dist-info/RECORD
