Metadata-Version: 2.3
Name: pytimetk
Version: 2.4.0
Summary: The time series toolkit for Python.
License: MIT
Keywords: time series,forecasting,machine learning,data science
Author: Business Science
Author-email: info@business-science.io
Maintainer: Matt Dancho
Maintainer-email: mdancho@business-science.io
Requires-Python: >=3.9
Classifier: License :: OSI Approved :: MIT License
Classifier: Programming Language :: Python :: 3
Classifier: Programming Language :: Python :: 3.9
Classifier: Programming Language :: Python :: 3.10
Classifier: Programming Language :: Python :: 3.11
Classifier: Programming Language :: Python :: 3.12
Classifier: Programming Language :: Python :: 3.13
Provides-Extra: gpu
Provides-Extra: gpu-cu12
Provides-Extra: regime-backends
Requires-Dist: adjusttext (>=0.8)
Requires-Dist: cudf-cu12 (>=24.10.0) ; (python_version >= "3.10" and platform_system == "Linux" and (platform_machine == "x86_64" or platform_machine == "aarch64")) and (extra == "gpu" or extra == "gpu-cu12")
Requires-Dist: hmmlearn (>=0.3.0)
Requires-Dist: holidays (>=0.33)
Requires-Dist: matplotlib (>=3.8.0)
Requires-Dist: pandas (>=2.0.0)
Requires-Dist: pandas-flavor (>=0.7.0)
Requires-Dist: patsy (>=0.5.6)
Requires-Dist: plotly (>=5.17.0)
Requires-Dist: plotnine (>=0.12.3)
Requires-Dist: polars (>=1.2.0)
Requires-Dist: pomegranate (<1.0) ; extra == "regime-backends"
Requires-Dist: pyarrow (>=16.1.0)
Requires-Dist: ray (>=2.10.0)
Requires-Dist: scikit-learn (>=1.5.2)
Requires-Dist: statsmodels (>=0.14.0)
Requires-Dist: timebasedcv (>=0.3)
Requires-Dist: tqdm (>=4.66.1)
Requires-Dist: tsfeatures (>=0.4.5)
Requires-Dist: xarray (>=2024.6.0)
Project-URL: Documentation, https://business-science.github.io/pytimetk/reference/
Project-URL: Homepage, https://business-science.github.io/pytimetk/
Project-URL: Repository, https://github.com/business-science/pytimetk
